src/dec_inicializadora_ADENEB/__init__.py
src/dec_inicializadora_ADENEB/dec_inicializadora.py
dec_inicilizadora_adeneb-0.0.1.dist-info/METADATA
dec_inicilizadora_adeneb-0.0.1.dist-info/WHEEL
dec_inicilizadora_adeneb-0.0.1.dist-info/licenses/LICENSE
dec_inicilizadora_adeneb-0.0.1.dist-info/RECORD
