Metadata-Version: 2.1
Name: dec_inicilizadora_ADENEB
Version: 0.0.1
Summary: class decorator of self variable initializer of class constructor
Project-URL: Homepage, https://github.com/agustinlucchelli/dec_inicializadora/tree/main
Author-email: Agustin <alucchelli@fi.uba.ar>
License-File: LICENSE
Classifier: License :: OSI Approved :: MIT License
Classifier: Operating System :: OS Independent
Classifier: Programming Language :: Python :: 3
Requires-Python: >=3.7
